{
    "steam_vr": [
        {
            "x": "2016-03",
            "y": 53
        },
        {
            "x": "2016-04",
            "y": 696
        },
        {
            "x": "2016-05",
            "y": 1564
        },
        {
            "x": "2016-06",
            "y": 1858
        },
        {
            "x": "2016-07",
            "y": 2099
        },
        {
            "x": "2016-08",
            "y": 2049
        },
        {
            "x": "2016-09",
            "y": 2114
        },
        {
            "x": "2016-10",
            "y": 2275
        },
        {
            "x": "2016-11",
            "y": 2554
        },
        {
            "x": "2016-12",
            "y": 3628
        },
        {
            "x": "2017-01",
            "y": 3579
        },
        {
            "x": "2017-02",
            "y": 3564
        },
        {
            "x": "2017-03",
            "y": 3181
        },
        {
            "x": "2017-04",
            "y": 3982
        },
        {
            "x": "2017-05",
            "y": 4616
        },
        {
            "x": "2017-06",
            "y": 5167
        },
        {
            "x": "2017-07",
            "y": 5315
        },
        {
            "x": "2017-08",
            "y": 5484
        },
        {
            "x": "2017-09",
            "y": 5599
        },
        {
            "x": "2017-10",
            "y": 5657
        },
        {
            "x": "2017-11",
            "y": 6026
        },
        {
            "x": "2017-12",
            "y": 8736
        },
        {
            "x": "2018-01",
            "y": 8680
        },
        {
            "x": "2018-02",
            "y": 7541
        },
        {
            "x": "2018-03",
            "y": 7331
        },
        {
            "x": "2018-04",
            "y": 8670
        },
        {
            "x": "2018-05",
            "y": 8835
        },
        {
            "x": "2018-06",
            "y": 9215
        },
        {
            "x": "2018-07",
            "y": 9065
        },
        {
            "x": "2018-08",
            "y": 9301
        },
        {
            "x": "2018-09",
            "y": 9138
        },
        {
            "x": "2018-10",
            "y": 9064
        },
        {
            "x": "2018-11",
            "y": 9833
        },
        {
            "x": "2018-12",
            "y": 12688
        },
        {
            "x": "2019-01",
            "y": 13177
        },
        {
            "x": "2019-02",
            "y": 11477
        },
        {
            "x": "2019-03",
            "y": 11631
        },
        {
            "x": "2019-04",
            "y": 10892
        },
        {
            "x": "2019-05",
            "y": 11370
        },
        {
            "x": "2019-06",
            "y": 12169
        },
        {
            "x": "2019-07",
            "y": 11635
        },
        {
            "x": "2019-08",
            "y": 11708
        },
        {
            "x": "2019-09",
            "y": 11152
        },
        {
            "x": "2019-10",
            "y": 11276
        },
        {
            "x": "2019-11",
            "y": 12073
        },
        {
            "x": "2019-12",
            "y": 17273
        },
        {
            "x": "2020-01",
            "y": 16513
        },
        {
            "x": "2020-02",
            "y": 14558
        },
        {
            "x": "2020-03",
            "y": 18603
        },
        {
            "x": "2020-04",
            "y": 16456
        },
        {
            "x": "2020-05",
            "y": 14094
        },
        {
            "x": "2020-06",
            "y": 13873
        },
        {
            "x": "2020-07",
            "y": 15184
        },
        {
            "x": "2020-08",
            "y": 14345
        },
        {
            "x": "2020-09",
            "y": 13266
        }
    ],
    "2020-07": [
        {
            "x": "01",
            "y": 14802
        },
        {
            "x": "02",
            "y": 14811
        },
        {
            "x": "03",
            "y": 16645
        },
        {
            "x": "04",
            "y": 17304
        },
        {
            "x": "05",
            "y": 16935
        },
        {
            "x": "06",
            "y": 14593
        },
        {
            "x": "07",
            "y": 14205
        },
        {
            "x": "08",
            "y": 14466
        },
        {
            "x": "09",
            "y": 14460
        },
        {
            "x": "10",
            "y": 15604
        },
        {
            "x": "11",
            "y": 17725
        },
        {
            "x": "12",
            "y": 16995
        },
        {
            "x": "13",
            "y": 14855
        },
        {
            "x": "14",
            "y": 14539
        },
        {
            "x": "15",
            "y": 14338
        },
        {
            "x": "16",
            "y": 14357
        },
        {
            "x": "17",
            "y": 15298
        },
        {
            "x": "18",
            "y": 16889
        },
        {
            "x": "19",
            "y": 16595
        },
        {
            "x": "20",
            "y": 14422
        },
        {
            "x": "21",
            "y": 14156
        },
        {
            "x": "22",
            "y": 13889
        },
        {
            "x": "23",
            "y": 14159
        },
        {
            "x": "24",
            "y": 14902
        },
        {
            "x": "25",
            "y": 17014
        },
        {
            "x": "26",
            "y": 16513
        },
        {
            "x": "27",
            "y": 14324
        },
        {
            "x": "28",
            "y": 13956
        },
        {
            "x": "29",
            "y": 13906
        },
        {
            "x": "30",
            "y": 13868
        },
        {
            "x": "31",
            "y": 14183
        }
    ],
    "2020-08": [
        {
            "x": "01",
            "y": 16282
        },
        {
            "x": "02",
            "y": 16627
        },
        {
            "x": "03",
            "y": 14827
        },
        {
            "x": "04",
            "y": 14412
        },
        {
            "x": "05",
            "y": 13666
        },
        {
            "x": "06",
            "y": 13694
        },
        {
            "x": "07",
            "y": 13988
        },
        {
            "x": "08",
            "y": 15917
        },
        {
            "x": "09",
            "y": 15757
        },
        {
            "x": "10",
            "y": 13868
        },
        {
            "x": "11",
            "y": 13302
        },
        {
            "x": "12",
            "y": 13044
        },
        {
            "x": "13",
            "y": 13175
        },
        {
            "x": "14",
            "y": 14101
        },
        {
            "x": "15",
            "y": 15863
        },
        {
            "x": "16",
            "y": 15682
        },
        {
            "x": "17",
            "y": 13366
        },
        {
            "x": "18",
            "y": 13053
        },
        {
            "x": "19",
            "y": 13174
        },
        {
            "x": "20",
            "y": 13088
        },
        {
            "x": "21",
            "y": 13752
        },
        {
            "x": "22",
            "y": 16131
        },
        {
            "x": "23",
            "y": 15763
        },
        {
            "x": "24",
            "y": 13405
        },
        {
            "x": "25",
            "y": 13378
        },
        {
            "x": "26",
            "y": 12751
        },
        {
            "x": "27",
            "y": 12967
        },
        {
            "x": "28",
            "y": 13917
        },
        {
            "x": "29",
            "y": 16798
        },
        {
            "x": "30",
            "y": 15744
        },
        {
            "x": "31",
            "y": 13190
        }
    ],
    "2020-09": [
        {
            "x": "01",
            "y": 12661
        },
        {
            "x": "02",
            "y": 12342
        },
        {
            "x": "03",
            "y": 12434
        },
        {
            "x": "04",
            "y": 13298
        },
        {
            "x": "05",
            "y": 16033
        },
        {
            "x": "06",
            "y": 15608
        },
        {
            "x": "07",
            "y": 14556
        },
        {
            "x": "08",
            "y": 12440
        },
        {
            "x": "09",
            "y": 11753
        },
        {
            "x": "10",
            "y": 11978
        },
        {
            "x": "11",
            "y": 12972
        },
        {
            "x": "12",
            "y": 16193
        },
        {
            "x": "13",
            "y": 15216
        },
        {
            "x": "14",
            "y": 12128
        },
        {
            "x": "15",
            "y": 11603
        },
        {
            "x": "16",
            "y": 11421
        },
        {
            "x": "17",
            "y": 11790
        },
        {
            "x": "18",
            "y": 13394
        },
        {
            "x": "19",
            "y": 16254
        },
        {
            "x": "20",
            "y": 15365
        },
        {
            "x": "21",
            "y": 12166
        },
        {
            "x": "22",
            "y": 11622
        },
        {
            "x": "23",
            "y": 11661
        },
        {
            "x": "24",
            "y": 11533
        },
        {
            "x": "25",
            "y": 13209
        },
        {
            "x": "26",
            "y": 16495
        },
        {
            "x": "27",
            "y": 15413
        },
        {
            "x": "28",
            "y": 12103
        },
        {
            "x": "29",
            "y": 12475
        },
        {
            "x": "30",
            "y": 11868
        }
    ],
    "top10": {
        "games": [
            "Beat Saber",
            "Half-Life: Alyx",
            "Pavlov VR",
            "Rec Room",
            "Blade and Sorcery",
            "The Walking Dead",
            "Hot Dogs",
            "BONEWORKS",
            "Skyrim VR",
            "VirtualCast"
        ],
        "max_players": [
            2605,
            1137,
            1074,
            885,
            696,
            653,
            610,
            446,
            376,
            279
        ],
        "avg_players": [
            1994.0,
            866.0,
            924.0,
            752.0,
            557.0,
            450.0,
            418.0,
            365.0,
            263.0,
            93.0
        ]
    }
}